gator/__init__.py
gator/arguments.py
gator/checkers.py
gator/checks/__init__.py
gator/checks/check_ConfirmFileExists.py
gator/checks/check_CountCommandOutput.py
gator/checks/check_CountCommits.py
gator/checks/check_CountFileLines.py
gator/checks/check_CountFileParagraphs.py
gator/checks/check_CountFileWords.py
gator/checks/check_CountMarkdownTags.py
gator/checks/check_CountMultipleLineComments.py
gator/checks/check_CountParagraphWords.py
gator/checks/check_CountSingleLineComments.py
gator/checks/check_ExecuteCommand.py
gator/checks/check_ListChecks.py
gator/checks/check_MatchCommandFragment.py
gator/checks/check_MatchCommandRegex.py
gator/checks/check_MatchFileFragment.py
gator/checks/check_MatchFileRegex.py
gator/comments.py
gator/constants.py
gator/description.py
gator/display.py
gator/entities.py
gator/exceptions.py
gator/files.py
gator/fragments.py
gator/invoke.py
gator/leave.py
gator/markdown.py
gator/orchestrate.py
gator/report.py
gator/repository.py
gator/run.py
gator/util.py
gatorgrader.py
gatorgrader-1.1.1.dist-info/entry_points.txt
gatorgrader-1.1.1.dist-info/LICENSE.md
gatorgrader-1.1.1.dist-info/WHEEL
gatorgrader-1.1.1.dist-info/METADATA
gatorgrader-1.1.1.dist-info/RECORD
