Metadata-Version: 2.1
Name: gatorgrader
Version: 1.1.1
Summary: Automated Grading Tool that Checks the Work of Writers and Programmers
Home-page: https://github.com/GatorEducator/gatorgrader
License: GPL-3.0
Keywords: grading,education,allegheny
Author: Gregory Kapfhammer
Author-email: gkapfham@allegheny.edu
Requires-Python: >=3.7.2,<4.0
Classifier: Development Status :: 5 - Production/Stable
Classifier: Environment :: Console
Classifier: License :: OSI Approved :: GNU General Public License v3 (GPLv3)
Classifier: License :: OSI Approved :: GNU General Public License v3 or later (GPLv3+)
Classifier: Operating System :: OS Independent
Classifier: Programming Language :: Python :: 3
Classifier: Programming Language :: Python :: 3.8
Classifier: Programming Language :: Python :: 3.9
Classifier: Programming Language :: Python :: 3.10
Classifier: Programming Language :: Python :: 3.11
Classifier: Topic :: Education :: Testing
Classifier: Topic :: Utilities
Requires-Dist: GitPython (>=3.1.27,<4.0.0)
Requires-Dist: commonmark (>=0.9.1,<0.10.0)
Requires-Dist: num2words (>=0.5.10,<0.6.0)
Requires-Dist: pluginbase (>=1.0.1,<2.0.0)
Requires-Dist: requests (>=2.28.1,<3.0.0)
Project-URL: Bug Tracker, https://github.com/GatorEducator/gatorgrader/issues
Project-URL: Documentation, https://github.com/GatorEducator/gatorgrader
Project-URL: Repository, https://github.com/GatorEducator/gatorgrader
